certbot_dns_cfproxy/__init__.py
certbot_dns_cfproxy/dns_cfproxy.py
certbot_dns_cfproxy-0.0.2.dist-info/METADATA
certbot_dns_cfproxy-0.0.2.dist-info/WHEEL
certbot_dns_cfproxy-0.0.2.dist-info/entry_points.txt
certbot_dns_cfproxy-0.0.2.dist-info/top_level.txt
certbot_dns_cfproxy-0.0.2.dist-info/RECORD
